AQIPython/__init__.py
AQIPython/aqi_Calc.py
AQIPython/breakPoints.py
AQIPython/errorCustom.py
AQIPython/unitOperations.py
AQIPython-1.0.1.dist-info/LICENSE
AQIPython-1.0.1.dist-info/METADATA
AQIPython-1.0.1.dist-info/WHEEL
AQIPython-1.0.1.dist-info/top_level.txt
AQIPython-1.0.1.dist-info/RECORD
