Metadata-Version: 2.1
Name: AQIPython
Version: 1.0.1
Summary: A Multistandard python AQI calculator library 
Home-page: https://github.com/Spritan/AQIPython
Author: Spritan
Author-email: proypabsab@gmail.com
License: MIT
Keywords: AQI,Air Quality,Sensors,IOT
Platform: UNKNOWN
Classifier: License :: OSI Approved :: MIT License
Classifier: Development Status :: 5 - Production/Stable
Classifier: Intended Audience :: Healthcare Industry
Classifier: Programming Language :: Python
Classifier: Operating System :: OS Independent
Provides-Extra: dev
License-File: LICENSE
